lazypandas/__init__.py
lazypandas/benchmarking.py
lazypandas/dataframe.py
lazypandas/execution.py
lazypandas/io_module.py
lazypandas/optimization.py
lazypandas-0.1.0.dist-info/METADATA
lazypandas-0.1.0.dist-info/WHEEL
lazypandas-0.1.0.dist-info/top_level.txt
lazypandas-0.1.0.dist-info/RECORD
