Metadata-Version: 2.1
Name: lazypandas
Version: 0.1.0
Summary: High-performance, lazy evaluation library for dataframes, optimized for large datasets and complex transformations.
Home-page: https://github.com/sidkris/lazypandas
Author: Siddharth Krishnan
Author-email: sid@sidkrishnan.com
Classifier: Programming Language :: Python :: 3
Classifier: License :: OSI Approved :: MIT License
Classifier: Operating System :: OS Independent
Classifier: Intended Audience :: Developers
Classifier: Intended Audience :: Science/Research
Classifier: Topic :: Software Development :: Libraries :: Python Modules
Classifier: Topic :: Scientific/Engineering :: Information Analysis
Requires-Python: >=3.6
Requires-Dist: pandas>=1.0
Requires-Dist: numpy>=1.18
Requires-Dist: psutil>=5.0
